README.md
setup.py
ifalib/__init__.py
ifalib/neighbour.c
ifalib/neighbour.py
ifalib/rdf.c
ifalib/rdf.py
ifalib.egg-info/PKG-INFO
ifalib.egg-info/SOURCES.txt
ifalib.egg-info/dependency_links.txt
ifalib.egg-info/top_level.txt