Metadata-Version: 1.0
Name: ifalib
Version: 0.4.2
Summary: Ilya Fedorov Analysis
Home-page: https://github.com/IlyaFed/ifalib/tree/master
Author: Ilya Fedorov
Author-email: ilya.d.fedorov@phystech.edu
License: MIT
Platform: UNKNOWN
